{
    "results": [
        {
            "name": {
                "title": "Mr",
                "first": "Clément",
                "last": "Meunier"
            },
            "email": "clement.meunier@example.com",
            "phone": "03-27-73-60-01",
            "picture": {
                "large": "https://randomuser.me/api/portraits/men/43.jpg",
                "medium": "https://randomuser.me/api/portraits/med/men/43.jpg",
                "thumbnail": "https://randomuser.me/api/portraits/thumb/men/43.jpg"
            },
            "nat": "FR"
        },
        {
            "name": {
                "title": "Mr",
                "first": "Clément",
                "last": "Meunier"
            },
            "email": "clement.meunier@example.com",
            "phone": "03-27-73-60-01",
            "picture": {
                "large": "https://randomuser.me/api/portraits/men/43.jpg",
                "medium": "https://randomuser.me/api/portraits/med/men/43.jpg",
                "thumbnail": "https://randomuser.me/api/portraits/thumb/men/43.jpg"
            },
            "nat": "FR"
        }
    ],
    "info": {
        "seed": "0588657a16dbdc38",
        "results": 2,
        "page": 1,
        "version": "1.4"
    }
}
